persian_tools/__init__.py
persian_tools/ordinal_suffix.py
persian_tools/separator.py
persian_tools/bank/__init__.py
persian_tools/bank/banks_code.py
persian_tools/bank/card_number.py
persian_tools/bank/exceptions.py
persian_tools/bank/sheba.py
persian_tools/bill/__init__.py
persian_tools/bill/exceptions.py
persian_tools/digits/__init__.py
persian_tools/digits/strings.py
persian_tools/legal_id/__init__.py
persian_tools/national_id/__init__.py
persian_tools/national_id/exceptions.py
persian_tools/national_id/places_code.py
persian_tools/phone_number/__init__.py
persian_tools/phone_number/exceptions.py
persian_tools/phone_number/operators.py
persian_tools/plate/__init__.py
persian_tools/plate/dataset.py
persian_tools/plate/exceptions.py
tests/__init__.py
tests/test_bank_card_number.py
tests/test_bank_sheba.py
tests/test_bill.py
tests/test_digis.py
tests/test_legal_id.py
tests/test_national_id.py
tests/test_ordinal_suffix.py
tests/test_phone_number.py
tests/test_plate.py
tests/test_separator.py
persian_tools-0.0.11.dist-info/LICENSE.txt
persian_tools-0.0.11.dist-info/METADATA
persian_tools-0.0.11.dist-info/WHEEL
persian_tools-0.0.11.dist-info/top_level.txt
persian_tools-0.0.11.dist-info/RECORD
