Metadata-Version: 2.1
Name: persian_tools
Version: 0.0.11
Summary: An anthology of a variety of tools for the Persian language in Python
Home-page: https://github.com/persian-tools/py-persian-tools
Download-URL: https://github.com/persian-tools/py-persian-tools/archive/v0.0.11.zip
Author: Ali Madihi (mrunderline)
Author-email: alimadihib@gmail.com
License: MIT
Keywords: digits,commas,iranian bank,card number,national id,national code,ordinal suffix
Classifier: Development Status :: 4 - Beta
Classifier: Environment :: Plugins
Classifier: Intended Audience :: Developers
Classifier: License :: OSI Approved :: MIT License
Classifier: Operating System :: OS Independent
Classifier: Programming Language :: Python :: 3.6
Classifier: Programming Language :: Python :: 3.7
Classifier: Programming Language :: Python :: 3.8
Classifier: Programming Language :: Python :: 3.9
Classifier: Programming Language :: Python :: 3.10
Classifier: Programming Language :: Python :: 3.11
Classifier: Topic :: Utilities
Requires-Python: >=3.6
License-File: LICENSE.txt
